{
    "SUPPORTED_LANGUAGES" : ["en", "de"],
    "AVAILABLE_LANGUAGES" : ["en-US", "en-GB", "bg", "zh-CN", "zh-TW", "hr", "cs", "da", "nl", "fi", "fr", "de", "el", "hi", "hu", "it", "ja", "ko", "lt", "no", "pl", "pt-BR", "ro", "ru", "es-ES", "sv-SE", "th", "tr", "uk", "vi"],
    "commandHandler" : {
        "MISSING_PERMISSIONS" : {
            "en" : "You are missing permissions [{0}]",
            "de" : "Dir fehlen berechtigungen [{0}]"
        },
        "WRONG" : {
            "en" : "Something went wrong",
            "de" : "Irgendetwas ist schiefgelaufen"
        },
        "PERMISSIONS_NEEDED" : {
            "en" : "This command requires `{0}` more (global) permission(s): ```diff\n{1}```Add them to my integration role to fix this.",
            "de" : "Dieser Command benötigt {0} weitere (globale) berechtigungen: ```diff\n{1}```Füge dieser meiner Integrierten Rolle hinzu um dies zu beheben."
        }
    }
}